{
  "updated_at": "2026-06-09T23:34:16Z",
  "comment": "빅테크 단독 약세(나스닥 vs S&P 디커플링).",
  "matched_rule": "tech_decouple",
  "indicators": [
    {
      "name": "S&P 500",
      "value": "7,387",
      "delta": "-0.26%",
      "direction": "down"
    },
    {
      "name": "Nasdaq",
      "value": "25,679",
      "delta": "-0.97%",
      "direction": "down"
    },
    {
      "name": "VIX",
      "value": "19.9",
      "delta": "+5.0%",
      "direction": "up"
    },
    {
      "name": "DXY",
      "value": "100.0",
      "delta": "-0.05%",
      "direction": "down"
    },
    {
      "name": "USD/JPY",
      "value": "160.40",
      "delta": "+0.14%",
      "direction": "up"
    },
    {
      "name": "10Y",
      "value": "4.53%",
      "delta": "-2bp",
      "direction": "down"
    },
    {
      "name": "Gold",
      "value": "4,251",
      "delta": "-1.96%",
      "direction": "down"
    },
    {
      "name": "WTI",
      "value": "89.17",
      "delta": "-2.33%",
      "direction": "down"
    },
    {
      "name": "BTC",
      "value": "61,694",
      "delta": "-2.21%",
      "direction": "down"
    }
  ]
}
